pas.plugins.keycloakgroups-1.0.0a2-py3.10-nspkg.pth
pas/plugins/keycloakgroups/__init__.py
pas/plugins/keycloakgroups/configure.zcml
pas/plugins/keycloakgroups/dependencies.zcml
pas/plugins/keycloakgroups/interfaces.py
pas/plugins/keycloakgroups/profiles.zcml
pas/plugins/keycloakgroups/setuphandlers.py
pas/plugins/keycloakgroups/testing.py
pas/plugins/keycloakgroups/controlpanel/__init__.py
pas/plugins/keycloakgroups/controlpanel/configure.zcml
pas/plugins/keycloakgroups/controlpanel/controlpanel.py
pas/plugins/keycloakgroups/locales/__init__.py
pas/plugins/keycloakgroups/locales/pas.plugins.keycloakgroups.pot
pas/plugins/keycloakgroups/locales/update.py
pas/plugins/keycloakgroups/locales/en/LC_MESSAGES/pas.plugins.keycloakgroups.po
pas/plugins/keycloakgroups/locales/es/LC_MESSAGES/pas.plugins.keycloakgroups.po
pas/plugins/keycloakgroups/plugins/__init__.py
pas/plugins/keycloakgroups/plugins/group.py
pas/plugins/keycloakgroups/plugins/plugin.py
pas/plugins/keycloakgroups/plugins/utils.py
pas/plugins/keycloakgroups/profiles/default/browserlayer.xml
pas/plugins/keycloakgroups/profiles/default/controlpanel.xml
pas/plugins/keycloakgroups/profiles/default/metadata.xml
pas/plugins/keycloakgroups/profiles/default/registry/.gitkeep
pas/plugins/keycloakgroups/profiles/default/registry/pas.plugins.keycloakgroups.interfaces.IKeycloakSettings.xml
pas/plugins/keycloakgroups/profiles/uninstall/browserlayer.xml
pas/plugins/keycloakgroups/subscribers/__init__.py
pas/plugins/keycloakgroups/subscribers/configure.zcml
pas/plugins/keycloakgroups/subscribers/settings.py
pas/plugins/keycloakgroups/upgrades/__init__.py
pas/plugins/keycloakgroups/upgrades/configure.zcml
pas/plugins/keycloakgroups/utils/__init__.py
pas/plugins/keycloakgroups/utils/setup.py
pas.plugins.keycloakgroups-1.0.0a2.dist-info/LICENSE.GPL
pas.plugins.keycloakgroups-1.0.0a2.dist-info/METADATA
pas.plugins.keycloakgroups-1.0.0a2.dist-info/WHEEL
pas.plugins.keycloakgroups-1.0.0a2.dist-info/entry_points.txt
pas.plugins.keycloakgroups-1.0.0a2.dist-info/namespace_packages.txt
pas.plugins.keycloakgroups-1.0.0a2.dist-info/top_level.txt
pas.plugins.keycloakgroups-1.0.0a2.dist-info/RECORD
