Metadata-Version: 2.1
Name: pas.plugins.keycloakgroups
Version: 1.0.0a2
Summary: Use groups from Keycloak inside Plone portals.
Home-page: https://github.com/collective/pas.plugins.keycloakgroups
Author: Érico Andrei
Author-email: ericof@plone.org
License: GPL version 2
Project-URL: PyPI, https://pypi.python.org/pypi/pas.plugins.keycloakgroups
Project-URL: Source, https://github.com/collective/pas.plugins.keycloakgroups
Project-URL: Issue Tracker, https://github.com/collective/pas.plugins.keycloakgroups/issues
Project-URL: Documentation, https://collective.github.io/pas.plugins.keycloakgroups
Keywords: Python Plone CMS Keycloak Authentication Zope
Classifier: Development Status :: 3 - Alpha
Classifier: Environment :: Web Environment
Classifier: Framework :: Plone
Classifier: Framework :: Plone :: Addon
Classifier: Framework :: Plone :: Distribution
Classifier: Framework :: Plone :: 6.0
Classifier: Programming Language :: Python
Classifier: Programming Language :: Python :: 3.8
Classifier: Programming Language :: Python :: 3.9
Classifier: Programming Language :: Python :: 3.10
Classifier: Programming Language :: Python :: 3.11
Classifier: Operating System :: OS Independent
Classifier: License :: OSI Approved :: GNU General Public License v2 (GPLv2)
Requires-Python: >=3.8
License-File: LICENSE.GPL
Requires-Dist: setuptools
Requires-Dist: Plone
Requires-Dist: plone.api
Requires-Dist: plone.restapi
Requires-Dist: python-keycloak
Provides-Extra: test
Requires-Dist: zest.releaser[recommended] ; extra == 'test'
Requires-Dist: zestreleaser.towncrier ; extra == 'test'
Requires-Dist: plone.app.testing ; extra == 'test'
Requires-Dist: plone.testing ; extra == 'test'
Requires-Dist: plone.restapi[test] ; extra == 'test'
Requires-Dist: pytest ; extra == 'test'
Requires-Dist: pytest-cov ; extra == 'test'
Requires-Dist: pytest-plone >=0.2.0 ; extra == 'test'
Requires-Dist: pytest-docker ; extra == 'test'
Requires-Dist: pas.plugins.oidc >=2.0.0a1 ; extra == 'test'
